{
  "average_value": false,
  "element": null,
  "max_value": false,
  "min_value": false,
  "name": "sys_update_version",
  "parent": null,
  "position": null,
  "relationship": null,
  "sum": false,
  "sys_class_name": "sys_ui_list",
  "sys_created_by": "admin",
  "sys_created_on": "2019-11-21 02:39:07",
  "sys_id": "c70dfc7cdb190010343f58b3ca961990",
  "sys_mod_count": 0,
  "sys_name": null,
  "sys_package": null,
  "sys_policy": null,
  "sys_scope": "19190fabdbebd300dfa9b94ffe96193e",
  "sys_update_name": null,
  "sys_updated_by": "admin",
  "sys_updated_on": "2019-11-21 02:39:07",
  "view": "Default view",
  "view_name": null
}
